tenma_power_supply/__init__.py
tenma_power_supply/driver.py
tenma_power_supply/sipyco_controller.py
tenma_power_supply-1.2.3.dist-info/METADATA
tenma_power_supply-1.2.3.dist-info/WHEEL
tenma_power_supply-1.2.3.dist-info/entry_points.txt
tenma_power_supply-1.2.3.dist-info/RECORD
