Metadata-Version: 2.4
Name: tenma-power-supply
Version: 1.2.3
Summary: Driver for the TENMA power supply
Author: Charles Baynham
Author-email: c.baynham@imperial.ac.uk
Requires-Python: >=3.9,<3.13
Classifier: Programming Language :: Python :: 3
Classifier: Programming Language :: Python :: 3.9
Classifier: Programming Language :: Python :: 3.10
Classifier: Programming Language :: Python :: 3.11
Classifier: Programming Language :: Python :: 3.12
Requires-Dist: generic-scpi-driver (>=1.5,<2.0)
Requires-Dist: retry (>=0.9.2,<0.10.0)
